data_simulator/__init__.py
data_simulator/document_processor.py
data_simulator/llm.py
data_simulator/prompts.py
data_simulator/simulator.py
data_simulator/utils.py
llm_data_simulator-0.1.0.dist-info/licenses/LICENSE
llm_data_simulator-0.1.0.dist-info/METADATA
llm_data_simulator-0.1.0.dist-info/WHEEL
llm_data_simulator-0.1.0.dist-info/top_level.txt
llm_data_simulator-0.1.0.dist-info/RECORD
