Metadata-Version: 2.4
Name: llm-data-simulator
Version: 0.1.0
Summary: Generate synthetic evaluation datasets from your own documents.
Author-email: Tahmid <tahmid@langwatch.ai>
License: MIT
Project-URL: Repository, https://github.com/langwatch/data-simulator
Project-URL: Documentation, https://github.com/langwatch/data-simulator
Project-URL: Bug Tracker, https://github.com/langwatch/data-simulator/issues
Classifier: Programming Language :: Python :: 3
Classifier: License :: OSI Approved :: MIT License
Classifier: Operating System :: OS Independent
Classifier: Topic :: Scientific/Engineering :: Artificial Intelligence
Classifier: Intended Audience :: Developers
Classifier: Development Status :: 4 - Beta
Requires-Python: >=3.8
License-File: LICENSE
Requires-Dist: openai>=1.0.0
Requires-Dist: tqdm
Requires-Dist: pandas
Requires-Dist: python-dotenv
Requires-Dist: langchain_community
Requires-Dist: langchain
Requires-Dist: pypdf
Dynamic: license-file
